RealToolkits/ExcelMeta.py
RealToolkits/__init__.py
RealToolkits/excel_meta.dll
RealToolkits/excel_meta.so
RealToolkits/realDecorator.py
RealToolkits/realDistrabutedLock.py
RealToolkits/realEmail.py
RealToolkits/realFileToolkits.py
RealToolkits/realLog.py
RealToolkits/realTblToolkits.py
RealToolkits/type_kits.py
RealToolkits-1.4.2.dist-info/LICENSE
RealToolkits-1.4.2.dist-info/METADATA
RealToolkits-1.4.2.dist-info/WHEEL
RealToolkits-1.4.2.dist-info/top_level.txt
RealToolkits-1.4.2.dist-info/RECORD
