Metadata-Version: 2.1
Name: RealToolkits
Version: 1.4.2
Summary: A set of code candy.
Home-page: https://e.coding.net/dataframe/real_py/PyPI_src_of_real.git
Author: Real He
Author-email: i874u@hotmail.com
License: BSD
Platform: UNKNOWN
Classifier: Development Status :: 5 - Production/Stable
Classifier: Operating System :: OS Independent
Classifier: License :: OSI Approved :: BSD License
Classifier: Programming Language :: Python
Classifier: Programming Language :: Python :: 3
Classifier: Programming Language :: Python :: 3.6
Classifier: Programming Language :: Python :: 3.7
Classifier: Programming Language :: Python :: 3.8
Classifier: Programming Language :: Python :: 3.9
Classifier: Programming Language :: Python :: Implementation :: CPython
Requires-Python: >=3.6.0
Requires-Dist: numpy
Requires-Dist: xlrd
Requires-Dist: redis
Requires-Dist: chardet
Requires-Dist: pandas
